[
  {
    "description": "",
    "elements": [
      {
        "description": "",
        "id": "as-a-user-i-expect-to-be-able-to-create-contacts;as-a-user-i-expect-to-be-able-to-create-a-new-contact",
        "keyword": "Scenario",
        "line": 6,
        "name": "As a user I expect to be able to create a new contact",
        "steps": [
          {
            "keyword": "Before",
            "hidden": true,
            "result": {
              "status": "passed",
              "duration": 2750261700
            }
          },
          {
            "arguments": [],
            "keyword": "Given ",
            "line": 7,
            "name": "I am on the \"home\" page",
            "match": {
              "location": "src\\step-definitions\\navigation.ts:8"
            },
            "result": {
              "status": "passed",
              "duration": 4061907100
            }
          },
          {
            "arguments": [],
            "keyword": "And ",
            "line": 8,
            "name": "I click the \"create\" button",
            "match": {
              "location": "src\\step-definitions\\click.ts:10"
            },
            "result": {
              "status": "passed",
              "duration": 561343500
            }
          },
          {
            "arguments": [],
            "keyword": "Then ",
            "line": 9,
            "name": "I am directed to the \"create contact\" page",
            "match": {
              "location": "src\\step-definitions\\navigation.ts:25"
            },
            "result": {
              "status": "passed",
              "duration": 5478000
            }
          },
          {
            "arguments": [],
            "keyword": "And ",
            "line": 10,
            "name": "the \"create contact header\" should contain the text \"Create Contact\"",
            "match": {
              "location": "src\\step-definitions\\assertions\\verify-element-value.ts:10"
            },
            "result": {
              "status": "passed",
              "duration": 127473599
            }
          },
          {
            "arguments": [],
            "keyword": "And ",
            "line": 11,
            "name": "I fill in the \"name\" input with \"Ljubisha\"",
            "match": {
              "location": "src\\step-definitions\\form.ts:8"
            },
            "result": {
              "status": "passed",
              "duration": 232790100
            }
          },
          {
            "arguments": [],
            "keyword": "And ",
            "line": 12,
            "name": "I select the \"Male\" option from the \"gender\"",
            "match": {
              "location": "src\\step-definitions\\form.ts:32"
            },
            "result": {
              "status": "passed",
              "duration": 328651900
            }
          },
          {
            "arguments": [],
            "keyword": "And ",
            "line": 13,
            "name": "I fill in the \"phone\" input with \"361 888\"",
            "match": {
              "location": "src\\step-definitions\\form.ts:8"
            },
            "result": {
              "status": "passed",
              "duration": 188649599
            }
          },
          {
            "arguments": [],
            "keyword": "And ",
            "line": 14,
            "name": "I fill in the \"street\" input with \"fake street\"",
            "match": {
              "location": "src\\step-definitions\\form.ts:8"
            },
            "result": {
              "status": "passed",
              "duration": 173491900
            }
          },
          {
            "arguments": [],
            "keyword": "And ",
            "line": 15,
            "name": "I fill in the \"city\" input with \"Skopje\"",
            "match": {
              "location": "src\\step-definitions\\form.ts:8"
            },
            "result": {
              "status": "passed",
              "duration": 128826199
            }
          },
          {
            "arguments": [],
            "keyword": "And ",
            "line": 16,
            "name": "I click the \"save\" button",
            "match": {
              "location": "src\\step-definitions\\click.ts:10"
            },
            "result": {
              "status": "passed",
              "duration": 327449300
            }
          },
          {
            "arguments": [],
            "keyword": "And ",
            "line": 18,
            "name": "I am directed to the \"home\" page",
            "match": {
              "location": "src\\step-definitions\\navigation.ts:25"
            },
            "result": {
              "status": "passed",
              "duration": 978699
            }
          },
          {
            "arguments": [],
            "keyword": "And ",
            "line": 19,
            "name": "I fill in the \"search\" input with \"Ljubisha\"",
            "match": {
              "location": "src\\step-definitions\\form.ts:8"
            },
            "result": {
              "status": "passed",
              "duration": 149624899
            }
          },
          {
            "arguments": [],
            "keyword": "And ",
            "line": 20,
            "name": "the \"search\" should not equal the text \"Ljubish\"",
            "match": {
              "location": "src\\step-definitions\\assertions\\verify-element-value.ts:30"
            },
            "result": {
              "status": "passed",
              "duration": 30202300
            }
          },
          {
            "arguments": [],
            "keyword": "And ",
            "line": 21,
            "name": "the \"full name label\" should contain the text \"Name:\"",
            "match": {
              "location": "src\\step-definitions\\assertions\\verify-element-value.ts:10"
            },
            "result": {
              "status": "passed",
              "duration": 15657400
            }
          },
          {
            "arguments": [],
            "keyword": "And ",
            "line": 22,
            "name": "the \"name\" should equal the text \"Ljubisha\"",
            "match": {
              "location": "src\\step-definitions\\assertions\\verify-element-value.ts:30"
            },
            "result": {
              "status": "passed",
              "duration": 14505300
            }
          },
          {
            "arguments": [],
            "keyword": "And ",
            "line": 23,
            "name": "the \"gender label\" should contain the text \"Gender:\"",
            "match": {
              "location": "src\\step-definitions\\assertions\\verify-element-value.ts:10"
            },
            "result": {
              "status": "passed",
              "duration": 17267099
            }
          },
          {
            "arguments": [],
            "keyword": "And ",
            "line": 24,
            "name": "the \"gender\" should equal the text \"Male\"",
            "match": {
              "location": "src\\step-definitions\\assertions\\verify-element-value.ts:30"
            },
            "result": {
              "status": "passed",
              "duration": 15867300
            }
          },
          {
            "arguments": [],
            "keyword": "And ",
            "line": 25,
            "name": "the \"address label\" should contain the text \"Address:\"",
            "match": {
              "location": "src\\step-definitions\\assertions\\verify-element-value.ts:10"
            },
            "result": {
              "status": "passed",
              "duration": 15149100
            }
          },
          {
            "arguments": [],
            "keyword": "And ",
            "line": 26,
            "name": "the \"address\" should equal the text \"fake street, Skopje\"",
            "match": {
              "location": "src\\step-definitions\\assertions\\verify-element-value.ts:30"
            },
            "result": {
              "status": "passed",
              "duration": 13477500
            }
          },
          {
            "arguments": [],
            "keyword": "And ",
            "line": 27,
            "name": "the \"edit\" should be displayed",
            "match": {
              "location": "src\\step-definitions\\assertions\\verify-element-visibility.ts:9"
            },
            "result": {
              "status": "passed",
              "duration": 26220100
            }
          },
          {
            "arguments": [],
            "keyword": "And ",
            "line": 28,
            "name": "the \"delete\" should be displayed",
            "match": {
              "location": "src\\step-definitions\\assertions\\verify-element-visibility.ts:9"
            },
            "result": {
              "status": "passed",
              "duration": 25197099
            }
          },
          {
            "keyword": "After",
            "hidden": true,
            "result": {
              "status": "passed",
              "duration": 1747650999
            }
          }
        ],
        "tags": [
          {
            "name": "@smoke",
            "line": 3
          },
          {
            "name": "@regression",
            "line": 4
          }
        ],
        "type": "scenario"
      }
    ],
    "id": "as-a-user-i-expect-to-be-able-to-create-contacts",
    "line": 1,
    "keyword": "Feature",
    "name": "As a user I expect to be able to create contacts",
    "tags": [],
    "uri": "src\\features\\create-contact.feature"
  },
  {
    "description": "",
    "elements": [
      {
        "description": "",
        "id": "as-a-user-i-expect-to-be-able-to-navigate-to-the-home-page;as-a-user-i-expect-to-be-able-to-see-contacts",
        "keyword": "Scenario",
        "line": 6,
        "name": "As a user I expect to be able to see contacts",
        "steps": [
          {
            "keyword": "Before",
            "hidden": true,
            "result": {
              "status": "passed",
              "duration": 2764255000
            }
          },
          {
            "arguments": [],
            "keyword": "Given ",
            "line": 7,
            "name": "I am on the \"home\" page",
            "match": {
              "location": "src\\step-definitions\\navigation.ts:8"
            },
            "result": {
              "status": "passed",
              "duration": 3633183799
            }
          },
          {
            "arguments": [],
            "keyword": "And ",
            "line": 8,
            "name": "the \"header logo\" should be displayed",
            "match": {
              "location": "src\\step-definitions\\assertions\\verify-element-visibility.ts:9"
            },
            "result": {
              "status": "passed",
              "duration": 277751000
            }
          },
          {
            "arguments": [],
            "keyword": "Then ",
            "line": 9,
            "name": "the \"contacts header\" should contain the text \"Contacts\"",
            "match": {
              "location": "src\\step-definitions\\assertions\\verify-element-value.ts:10"
            },
            "result": {
              "status": "passed",
              "duration": 192936999
            }
          },
          {
            "keyword": "After",
            "hidden": true,
            "result": {
              "status": "passed",
              "duration": 3614956700
            }
          }
        ],
        "tags": [
          {
            "name": "@smoke",
            "line": 4
          },
          {
            "name": "@regression",
            "line": 5
          }
        ],
        "type": "scenario"
      },
      {
        "description": "",
        "id": "as-a-user-i-expect-to-be-able-to-navigate-to-the-home-page;as-a-user-i-don't-expect-to-see-a-contact-that-does-not-exist",
        "keyword": "Scenario",
        "line": 13,
        "name": "As a user I don't expect to see a contact that does not exist",
        "steps": [
          {
            "keyword": "Before",
            "hidden": true,
            "result": {
              "status": "passed",
              "duration": 3860266999
            }
          },
          {
            "arguments": [],
            "keyword": "Given ",
            "line": 14,
            "name": "I am on the \"home\" page",
            "match": {
              "location": "src\\step-definitions\\navigation.ts:8"
            },
            "result": {
              "status": "passed",
              "duration": 3557030300
            }
          },
          {
            "arguments": [],
            "keyword": "And ",
            "line": 15,
            "name": "I fill in the \"search\" input with \"Funky Name\"",
            "match": {
              "location": "src\\step-definitions\\form.ts:8"
            },
            "result": {
              "status": "passed",
              "duration": 591440599
            }
          },
          {
            "arguments": [],
            "keyword": "Then ",
            "line": 16,
            "name": "the \"contact\" should not be displayed",
            "match": {
              "location": "src\\step-definitions\\assertions\\verify-element-visibility.ts:9"
            },
            "result": {
              "status": "passed",
              "duration": 52553400
            }
          },
          {
            "keyword": "After",
            "hidden": true,
            "result": {
              "status": "passed",
              "duration": 2534488900
            }
          }
        ],
        "tags": [
          {
            "name": "@smoke",
            "line": 11
          },
          {
            "name": "@regression",
            "line": 12
          }
        ],
        "type": "scenario"
      }
    ],
    "id": "as-a-user-i-expect-to-be-able-to-navigate-to-the-home-page",
    "line": 1,
    "keyword": "Feature",
    "name": "As a user I expect to be able to navigate to the home page",
    "tags": [],
    "uri": "src\\features\\home-page.feature"
  },
  {
    "description": "",
    "elements": [
      {
        "description": "",
        "id": "as-a-user-i-can-interact-with-checkboxes;as-a-user-i-can-interact-and-assert-checkboxes",
        "keyword": "Scenario",
        "line": 6,
        "name": "As a user I can interact and assert checkboxes",
        "steps": [
          {
            "keyword": "Before",
            "hidden": true,
            "result": {
              "status": "passed",
              "duration": 2672594099
            }
          },
          {
            "arguments": [],
            "keyword": "Given ",
            "line": 7,
            "name": "I am on the \"home\" page",
            "match": {
              "location": "src\\step-definitions\\navigation.ts:8"
            },
            "result": {
              "status": "passed",
              "duration": 3072697299
            }
          },
          {
            "arguments": [],
            "keyword": "And ",
            "line": 8,
            "name": "I click the \"playground\" button",
            "match": {
              "location": "src\\step-definitions\\click.ts:10"
            },
            "result": {
              "status": "passed",
              "duration": 664335800
            }
          },
          {
            "arguments": [],
            "keyword": "When ",
            "line": 9,
            "name": "I am directed to the \"playground\" page",
            "match": {
              "location": "src\\step-definitions\\navigation.ts:25"
            },
            "result": {
              "status": "passed",
              "duration": 6870700
            }
          },
          {
            "arguments": [],
            "keyword": "And ",
            "line": 10,
            "name": "the \"blue\" check box should not be checked",
            "match": {
              "location": "src\\step-definitions\\assertions\\verify-element-checked.ts:8"
            },
            "result": {
              "status": "passed",
              "duration": 3758556300
            }
          },
          {
            "arguments": [],
            "keyword": "And ",
            "line": 11,
            "name": "I check the \"green\" check box",
            "match": {
              "location": "src\\step-definitions\\check.ts:8"
            },
            "result": {
              "status": "passed",
              "duration": 578392799
            }
          },
          {
            "arguments": [],
            "keyword": "And ",
            "line": 12,
            "name": "I check the \"grey\" check box",
            "match": {
              "location": "src\\step-definitions\\check.ts:8"
            },
            "result": {
              "status": "passed",
              "duration": 280093000
            }
          },
          {
            "arguments": [],
            "keyword": "And ",
            "line": 13,
            "name": "the \"red\" check box should not be checked",
            "match": {
              "location": "src\\step-definitions\\assertions\\verify-element-checked.ts:8"
            },
            "result": {
              "status": "passed",
              "duration": 376370899
            }
          },
          {
            "arguments": [],
            "keyword": "And ",
            "line": 14,
            "name": "the \"purple\" check box should not be checked",
            "match": {
              "location": "src\\step-definitions\\assertions\\verify-element-checked.ts:8"
            },
            "result": {
              "status": "passed",
              "duration": 403065999
            }
          },
          {
            "arguments": [],
            "keyword": "And ",
            "line": 15,
            "name": "I uncheck the \"green\" check box",
            "match": {
              "location": "src\\step-definitions\\check.ts:8"
            },
            "result": {
              "status": "passed",
              "duration": 379766799
            }
          },
          {
            "arguments": [],
            "keyword": "And ",
            "line": 16,
            "name": "the \"green\" check box should not be checked",
            "match": {
              "location": "src\\step-definitions\\assertions\\verify-element-checked.ts:8"
            },
            "result": {
              "status": "passed",
              "duration": 49122300
            }
          },
          {
            "keyword": "After",
            "hidden": true,
            "result": {
              "status": "passed",
              "duration": 2222589800
            }
          }
        ],
        "tags": [
          {
            "name": "@smoke",
            "line": 3
          },
          {
            "name": "@regression",
            "line": 4
          }
        ],
        "type": "scenario"
      }
    ],
    "id": "as-a-user-i-can-interact-with-checkboxes",
    "line": 1,
    "keyword": "Feature",
    "name": "As a user I can interact with checkboxes",
    "tags": [],
    "uri": "src\\features\\playground\\checkboxes.feature"
  },
  {
    "description": "",
    "elements": [
      {
        "description": "",
        "id": "as-a-user-i-can-interact-with-iframes;as-a-user-i-can-interact-and-assert-on-iframes",
        "keyword": "Scenario",
        "line": 6,
        "name": "As a user I can interact and assert on IFrames",
        "steps": [
          {
            "keyword": "Before",
            "hidden": true,
            "result": {
              "status": "passed",
              "duration": 3124375599
            }
          },
          {
            "arguments": [],
            "keyword": "Given ",
            "line": 7,
            "name": "I am on the \"home\" page",
            "match": {
              "location": "src\\step-definitions\\navigation.ts:8"
            },
            "result": {
              "status": "passed",
              "duration": 2827616300
            }
          },
          {
            "arguments": [],
            "keyword": "And ",
            "line": 8,
            "name": "I click the \"playground\" button",
            "match": {
              "location": "src\\step-definitions\\click.ts:10"
            },
            "result": {
              "status": "passed",
              "duration": 654447899
            }
          },
          {
            "arguments": [],
            "keyword": "When ",
            "line": 9,
            "name": "I am directed to the \"playground\" page",
            "match": {
              "location": "src\\step-definitions\\navigation.ts:25"
            },
            "result": {
              "status": "passed",
              "duration": 3886999
            }
          },
          {
            "arguments": [],
            "keyword": "And ",
            "line": 10,
            "name": "I fill in the \"search\" input on the \"basic iframe\" iframe with \"Abraham Perry\"",
            "match": {
              "location": "src\\step-definitions\\iframe.ts:8"
            },
            "result": {
              "status": "passed",
              "duration": 3799252799
            }
          },
          {
            "arguments": [],
            "keyword": "And ",
            "line": 11,
            "name": "the \"contact\" on the \"basic iframe\" iframe should be displayed",
            "match": {
              "location": "src\\step-definitions\\assertions\\verify-iframe.ts:8"
            },
            "result": {
              "status": "passed",
              "duration": 1370589799
            }
          },
          {
            "arguments": [],
            "keyword": "And ",
            "line": 12,
            "name": "the \"full name label\" on the \"basic iframe\" iframe should contain the text \"Name:\"",
            "match": {
              "location": "src\\step-definitions\\assertions\\verify-iframe.ts:29"
            },
            "result": {
              "status": "passed",
              "duration": 114374900
            }
          },
          {
            "arguments": [],
            "keyword": "And ",
            "line": 13,
            "name": "the \"name\" on the \"basic iframe\" iframe should equal the text \"Abraham Perry\"",
            "match": {
              "location": "src\\step-definitions\\assertions\\verify-iframe.ts:50"
            },
            "result": {
              "status": "passed",
              "duration": 108472699
            }
          },
          {
            "arguments": [],
            "keyword": "And ",
            "line": 14,
            "name": "the \"gender label\" on the \"basic iframe\" iframe should contain the text \"Gender:\"",
            "match": {
              "location": "src\\step-definitions\\assertions\\verify-iframe.ts:29"
            },
            "result": {
              "status": "passed",
              "duration": 229001700
            }
          },
          {
            "arguments": [],
            "keyword": "And ",
            "line": 15,
            "name": "the \"gender\" on the \"basic iframe\" iframe should equal the text \"Male\"",
            "match": {
              "location": "src\\step-definitions\\assertions\\verify-iframe.ts:50"
            },
            "result": {
              "status": "passed",
              "duration": 91151400
            }
          },
          {
            "arguments": [],
            "keyword": "And ",
            "line": 16,
            "name": "the \"address label\" on the \"basic iframe\" iframe should contain the text \"Address:\"",
            "match": {
              "location": "src\\step-definitions\\assertions\\verify-iframe.ts:29"
            },
            "result": {
              "status": "passed",
              "duration": 139773999
            }
          },
          {
            "arguments": [],
            "keyword": "And ",
            "line": 17,
            "name": "the \"address\" on the \"basic iframe\" iframe should equal the text \"Ap #826-8849 Vulputate Street, Laramie\"",
            "match": {
              "location": "src\\step-definitions\\assertions\\verify-iframe.ts:50"
            },
            "result": {
              "status": "passed",
              "duration": 112591300
            }
          },
          {
            "arguments": [],
            "keyword": "And ",
            "line": 18,
            "name": "the \"edit\" on the \"basic iframe\" iframe should be displayed",
            "match": {
              "location": "src\\step-definitions\\assertions\\verify-iframe.ts:8"
            },
            "result": {
              "status": "passed",
              "duration": 105309499
            }
          },
          {
            "arguments": [],
            "keyword": "And ",
            "line": 19,
            "name": "the \"delete\" on the \"basic iframe\" iframe should be displayed",
            "match": {
              "location": "src\\step-definitions\\assertions\\verify-iframe.ts:8"
            },
            "result": {
              "status": "passed",
              "duration": 85274999
            }
          },
          {
            "keyword": "After",
            "hidden": true,
            "result": {
              "status": "passed",
              "duration": 5812672600
            }
          }
        ],
        "tags": [
          {
            "name": "@smoke",
            "line": 4
          },
          {
            "name": "@regression",
            "line": 5
          }
        ],
        "type": "scenario"
      }
    ],
    "id": "as-a-user-i-can-interact-with-iframes",
    "line": 1,
    "keyword": "Feature",
    "name": "As a user I can interact with IFrames",
    "tags": [],
    "uri": "src\\features\\playground\\iframes.feature"
  },
  {
    "description": "",
    "elements": [
      {
        "description": "",
        "id": "as-a-user-i-can-interact-with-autocomplete-inputs;as-a-user-i-can-interact-and-assert-on-autocomplete-inputs",
        "keyword": "Scenario",
        "line": 7,
        "name": "As a user I can interact and assert on autocomplete inputs",
        "steps": [
          {
            "keyword": "Before",
            "hidden": true,
            "result": {
              "status": "passed",
              "duration": 3355174200
            }
          },
          {
            "arguments": [],
            "keyword": "Given ",
            "line": 8,
            "name": "I am on the \"home\" page",
            "match": {
              "location": "src\\step-definitions\\navigation.ts:8"
            },
            "result": {
              "status": "passed",
              "duration": 2643898200
            }
          },
          {
            "arguments": [],
            "keyword": "And ",
            "line": 9,
            "name": "I click the \"playground\" button",
            "match": {
              "location": "src\\step-definitions\\click.ts:10"
            },
            "result": {
              "status": "passed",
              "duration": 717040199
            }
          },
          {
            "arguments": [],
            "keyword": "When ",
            "line": 10,
            "name": "I am directed to the \"playground\" page",
            "match": {
              "location": "src\\step-definitions\\navigation.ts:25"
            },
            "result": {
              "status": "passed",
              "duration": 451900
            }
          },
          {
            "arguments": [],
            "keyword": "And ",
            "line": 11,
            "name": "I fill in the \"movies\" input with \"The G\"",
            "match": {
              "location": "src\\step-definitions\\form.ts:8"
            },
            "result": {
              "status": "passed",
              "duration": 4187832300
            }
          },
          {
            "arguments": [],
            "keyword": "And ",
            "line": 12,
            "name": "I click the \"the godfather\" button",
            "match": {
              "location": "src\\step-definitions\\click.ts:10"
            },
            "result": {
              "status": "passed",
              "duration": 256192399
            }
          },
          {
            "arguments": [],
            "keyword": "And ",
            "line": 13,
            "name": "the \"movies\" should contain the value \"The Godfather\"",
            "match": {
              "location": "src\\step-definitions\\assertions\\verify-element-value.ts:48"
            },
            "result": {
              "status": "passed",
              "duration": 42064800
            }
          },
          {
            "arguments": [],
            "keyword": "And ",
            "line": 14,
            "name": "the \"movies\" should not contain the value \"The Godfather: Part II\"",
            "match": {
              "location": "src\\step-definitions\\assertions\\verify-element-value.ts:48"
            },
            "result": {
              "status": "passed",
              "duration": 44539099
            }
          },
          {
            "keyword": "After",
            "hidden": true,
            "result": {
              "status": "passed",
              "duration": 2529521100
            }
          }
        ],
        "tags": [
          {
            "name": "@smoke",
            "line": 4
          },
          {
            "name": "@regression",
            "line": 5
          }
        ],
        "type": "scenario"
      },
      {
        "description": "",
        "id": "as-a-user-i-can-interact-with-autocomplete-inputs;as-a-user-i-can-interact-and-assert-on-inputs",
        "keyword": "Scenario",
        "line": 19,
        "name": "As a user I can interact and assert on inputs",
        "steps": [
          {
            "keyword": "Before",
            "hidden": true,
            "result": {
              "status": "passed",
              "duration": 2031451199
            }
          },
          {
            "arguments": [],
            "keyword": "Given ",
            "line": 20,
            "name": "I am on the \"home\" page",
            "match": {
              "location": "src\\step-definitions\\navigation.ts:8"
            },
            "result": {
              "status": "passed",
              "duration": 2534458200
            }
          },
          {
            "arguments": [],
            "keyword": "And ",
            "line": 21,
            "name": "I click the \"playground\" button",
            "match": {
              "location": "src\\step-definitions\\click.ts:10"
            },
            "result": {
              "status": "passed",
              "duration": 2530570799
            }
          },
          {
            "arguments": [],
            "keyword": "When ",
            "line": 22,
            "name": "I am directed to the \"playground\" page",
            "match": {
              "location": "src\\step-definitions\\navigation.ts:25"
            },
            "result": {
              "status": "passed",
              "duration": 375000
            }
          },
          {
            "arguments": [],
            "keyword": "And ",
            "line": 23,
            "name": "the \"outlined required\" should equal the value \"Testing\"",
            "match": {
              "location": "src\\step-definitions\\assertions\\verify-element-value.ts:67"
            },
            "result": {
              "status": "passed",
              "duration": 562938099
            }
          },
          {
            "arguments": [],
            "keyword": "Then ",
            "line": 24,
            "name": "the \"outlined disabled\" should equal the value \"Talks\"",
            "match": {
              "location": "src\\step-definitions\\assertions\\verify-element-value.ts:67"
            },
            "result": {
              "status": "passed",
              "duration": 171632899
            }
          },
          {
            "arguments": [],
            "keyword": "And ",
            "line": 25,
            "name": "the \"outlined read only\" should equal the value \"Hub\"",
            "match": {
              "location": "src\\step-definitions\\assertions\\verify-element-value.ts:67"
            },
            "result": {
              "status": "passed",
              "duration": 861346100
            }
          },
          {
            "arguments": [],
            "keyword": "And ",
            "line": 26,
            "name": "the \"outlined required\" should be enabled",
            "match": {
              "location": "src\\step-definitions\\assertions\\verify-element-value.ts:86"
            },
            "result": {
              "status": "passed",
              "duration": 184119599
            }
          },
          {
            "arguments": [],
            "keyword": "And ",
            "line": 27,
            "name": "the \"outlined disabled\" should not be enabled",
            "match": {
              "location": "src\\step-definitions\\assertions\\verify-element-value.ts:86"
            },
            "result": {
              "status": "passed",
              "duration": 68073499
            }
          },
          {
            "arguments": [],
            "keyword": "And ",
            "line": 28,
            "name": "I fill in the \"outlined required\" input with \"Testing Talks Online\"",
            "match": {
              "location": "src\\step-definitions\\form.ts:8"
            },
            "result": {
              "status": "passed",
              "duration": 316567000
            }
          },
          {
            "arguments": [],
            "keyword": "And ",
            "line": 29,
            "name": "the \"outlined required\" should equal the value \"Testing Talks Online\"",
            "match": {
              "location": "src\\step-definitions\\assertions\\verify-element-value.ts:67"
            },
            "result": {
              "status": "passed",
              "duration": 104445800
            }
          },
          {
            "keyword": "After",
            "hidden": true,
            "result": {
              "status": "passed",
              "duration": 995713799
            }
          }
        ],
        "tags": [
          {
            "name": "@smoke",
            "line": 17
          },
          {
            "name": "@regression",
            "line": 18
          }
        ],
        "type": "scenario"
      },
      {
        "description": "",
        "id": "as-a-user-i-can-interact-with-autocomplete-inputs;as-a-user-i-can-interact-and-assert-on-input-validation",
        "keyword": "Scenario",
        "line": 34,
        "name": "As a user I can interact and assert on input validation",
        "steps": [
          {
            "keyword": "Before",
            "hidden": true,
            "result": {
              "status": "passed",
              "duration": 2343783199
            }
          },
          {
            "arguments": [],
            "keyword": "Given ",
            "line": 35,
            "name": "I am on the \"home\" page",
            "match": {
              "location": "src\\step-definitions\\navigation.ts:8"
            },
            "result": {
              "status": "passed",
              "duration": 2296886800
            }
          },
          {
            "arguments": [],
            "keyword": "And ",
            "line": 36,
            "name": "I click the \"playground\" button",
            "match": {
              "location": "src\\step-definitions\\click.ts:10"
            },
            "result": {
              "status": "passed",
              "duration": 626590500
            }
          },
          {
            "arguments": [],
            "keyword": "When ",
            "line": 37,
            "name": "I am directed to the \"playground\" page",
            "match": {
              "location": "src\\step-definitions\\navigation.ts:25"
            },
            "result": {
              "status": "passed",
              "duration": 605499
            }
          },
          {
            "arguments": [],
            "keyword": "And ",
            "line": 38,
            "name": "the \"outlined error\" should contain the text \"Error\"",
            "match": {
              "location": "src\\step-definitions\\assertions\\verify-element-value.ts:10"
            },
            "result": {
              "status": "passed",
              "duration": 3107593400
            }
          },
          {
            "arguments": [],
            "keyword": "And ",
            "line": 39,
            "name": "the \"outlined error text\" should contain the text \"Incorrect entry.\"",
            "match": {
              "location": "src\\step-definitions\\assertions\\verify-element-value.ts:10"
            },
            "result": {
              "status": "passed",
              "duration": 101312800
            }
          },
          {
            "keyword": "After",
            "hidden": true,
            "result": {
              "status": "passed",
              "duration": 1721500500
            }
          }
        ],
        "tags": [
          {
            "name": "@smoke",
            "line": 32
          },
          {
            "name": "@regression",
            "line": 33
          }
        ],
        "type": "scenario"
      }
    ],
    "id": "as-a-user-i-can-interact-with-autocomplete-inputs",
    "line": 1,
    "keyword": "Feature",
    "name": "As a user I can interact with autocomplete inputs",
    "tags": [],
    "uri": "src\\features\\playground\\inputs.feature"
  },
  {
    "description": "",
    "elements": [
      {
        "description": "",
        "id": "as-a-user-i-can-interact-with-radio-buttons;as-a-user-i-can-interact-and-assert-on-radio-buttons",
        "keyword": "Scenario",
        "line": 6,
        "name": "As a user I can interact and assert on radio buttons",
        "steps": [
          {
            "keyword": "Before",
            "hidden": true,
            "result": {
              "status": "passed",
              "duration": 3576830200
            }
          },
          {
            "arguments": [],
            "keyword": "Given ",
            "line": 7,
            "name": "I am on the \"home\" page",
            "match": {
              "location": "src\\step-definitions\\navigation.ts:8"
            },
            "result": {
              "status": "passed",
              "duration": 2257015599
            }
          },
          {
            "arguments": [],
            "keyword": "And ",
            "line": 8,
            "name": "I click the \"playground\" button",
            "match": {
              "location": "src\\step-definitions\\click.ts:10"
            },
            "result": {
              "status": "passed",
              "duration": 559483599
            }
          },
          {
            "arguments": [],
            "keyword": "When ",
            "line": 9,
            "name": "I am directed to the \"playground\" page",
            "match": {
              "location": "src\\step-definitions\\navigation.ts:25"
            },
            "result": {
              "status": "passed",
              "duration": 554100
            }
          },
          {
            "arguments": [],
            "keyword": "And ",
            "line": 10,
            "name": "the \"female label\" should not contain the text \"Male\"",
            "match": {
              "location": "src\\step-definitions\\assertions\\verify-element-value.ts:10"
            },
            "result": {
              "status": "passed",
              "duration": 1583434199
            }
          },
          {
            "arguments": [],
            "keyword": "And ",
            "line": 11,
            "name": "the \"male label\" should not contain the text \"Female\"",
            "match": {
              "location": "src\\step-definitions\\assertions\\verify-element-value.ts:10"
            },
            "result": {
              "status": "passed",
              "duration": 827414399
            }
          },
          {
            "arguments": [],
            "keyword": "And ",
            "line": 12,
            "name": "the \"female\" radio button should be checked",
            "match": {
              "location": "src\\step-definitions\\assertions\\verify-element-checked.ts:8"
            },
            "result": {
              "status": "passed",
              "duration": 148314899
            }
          },
          {
            "arguments": [],
            "keyword": "And ",
            "line": 13,
            "name": "the \"male\" radio button should not be checked",
            "match": {
              "location": "src\\step-definitions\\assertions\\verify-element-checked.ts:8"
            },
            "result": {
              "status": "passed",
              "duration": 64379100
            }
          },
          {
            "arguments": [],
            "keyword": "Then ",
            "line": 14,
            "name": "I check the \"male\" radio button",
            "match": {
              "location": "src\\step-definitions\\check.ts:8"
            },
            "result": {
              "status": "passed",
              "duration": 470063300
            }
          },
          {
            "arguments": [],
            "keyword": "And ",
            "line": 15,
            "name": "the \"male\" radio button should be checked",
            "match": {
              "location": "src\\step-definitions\\assertions\\verify-element-checked.ts:8"
            },
            "result": {
              "status": "passed",
              "duration": 101121899
            }
          },
          {
            "arguments": [],
            "keyword": "And ",
            "line": 16,
            "name": "the \"female\" radio button should not be checked",
            "match": {
              "location": "src\\step-definitions\\assertions\\verify-element-checked.ts:8"
            },
            "result": {
              "status": "passed",
              "duration": 53547999
            }
          },
          {
            "arguments": [],
            "keyword": "Then ",
            "line": 17,
            "name": "I check the \"female\" radio button",
            "match": {
              "location": "src\\step-definitions\\check.ts:8"
            },
            "result": {
              "status": "passed",
              "duration": 346824200
            }
          },
          {
            "arguments": [],
            "keyword": "And ",
            "line": 18,
            "name": "the \"female\" radio button should be checked",
            "match": {
              "location": "src\\step-definitions\\assertions\\verify-element-checked.ts:8"
            },
            "result": {
              "status": "passed",
              "duration": 44480799
            }
          },
          {
            "arguments": [],
            "keyword": "And ",
            "line": 19,
            "name": "the \"male\" radio button should not be checked",
            "match": {
              "location": "src\\step-definitions\\assertions\\verify-element-checked.ts:8"
            },
            "result": {
              "status": "passed",
              "duration": 46017899
            }
          },
          {
            "keyword": "After",
            "hidden": true,
            "result": {
              "status": "passed",
              "duration": 934780599
            }
          }
        ],
        "tags": [
          {
            "name": "@smoke",
            "line": 4
          },
          {
            "name": "@regression",
            "line": 5
          }
        ],
        "type": "scenario"
      }
    ],
    "id": "as-a-user-i-can-interact-with-radio-buttons",
    "line": 1,
    "keyword": "Feature",
    "name": "As a user I can interact with radio buttons",
    "tags": [],
    "uri": "src\\features\\playground\\radio-butons.feature"
  },
  {
    "description": "",
    "elements": [
      {
        "description": "",
        "id": "as-a-user-i-can-interact-with-tabs;as-a-user-i-can-interact-and-assert-on-new-tabs",
        "keyword": "Scenario",
        "line": 7,
        "name": "As a user I can interact and assert on new tabs",
        "steps": [
          {
            "keyword": "Before",
            "hidden": true,
            "result": {
              "status": "passed",
              "duration": 2769519499
            }
          },
          {
            "arguments": [],
            "keyword": "Given ",
            "line": 8,
            "name": "I am on the \"home\" page",
            "match": {
              "location": "src\\step-definitions\\navigation.ts:8"
            },
            "result": {
              "status": "passed",
              "duration": 2416405599
            }
          },
          {
            "arguments": [],
            "keyword": "And ",
            "line": 9,
            "name": "I click the \"playground\" button",
            "match": {
              "location": "src\\step-definitions\\click.ts:10"
            },
            "result": {
              "status": "passed",
              "duration": 689191299
            }
          },
          {
            "arguments": [],
            "keyword": "When ",
            "line": 10,
            "name": "I am directed to the \"playground\" page",
            "match": {
              "location": "src\\step-definitions\\navigation.ts:25"
            },
            "result": {
              "status": "passed",
              "duration": 1811799
            }
          },
          {
            "arguments": [],
            "keyword": "And ",
            "line": 11,
            "name": "I click the \"new tab\" button",
            "match": {
              "location": "src\\step-definitions\\click.ts:10"
            },
            "result": {
              "status": "passed",
              "duration": 2177798999
            }
          },
          {
            "arguments": [],
            "keyword": "And ",
            "line": 12,
            "name": "the \"2nd\" tab should contain the title \"Contacts\"",
            "match": {
              "location": "src\\step-definitions\\assertions\\verify-new-page.ts:8"
            },
            "result": {
              "status": "passed",
              "duration": 3051075400
            }
          },
          {
            "arguments": [],
            "keyword": "And ",
            "line": 13,
            "name": "the \"1st\" tab should contain the title \"Playground\"",
            "match": {
              "location": "src\\step-definitions\\assertions\\verify-new-page.ts:8"
            },
            "result": {
              "status": "passed",
              "duration": 1010541799
            }
          },
          {
            "arguments": [],
            "keyword": "And ",
            "line": 14,
            "name": "I fill in the \"search\" input on the \"2nd\" tab with \"Sloane Juarez\"",
            "match": {
              "location": "src\\step-definitions\\page.ts:8"
            },
            "result": {
              "status": "passed",
              "duration": 168907899
            }
          },
          {
            "arguments": [],
            "keyword": "And ",
            "line": 15,
            "name": "the \"contact\" on the \"2nd\" tab should be displayed",
            "match": {
              "location": "src\\step-definitions\\assertions\\verify-new-page.ts:29"
            },
            "result": {
              "status": "passed",
              "duration": 37371699
            }
          },
          {
            "arguments": [],
            "keyword": "And ",
            "line": 16,
            "name": "the \"full name label\" on the \"2nd\" tab should contain the text \"Name:\"",
            "match": {
              "location": "src\\step-definitions\\assertions\\verify-new-page.ts:51"
            },
            "result": {
              "status": "passed",
              "duration": 14287199
            }
          },
          {
            "arguments": [],
            "keyword": "And ",
            "line": 17,
            "name": "the \"name\" on the \"2nd\" tab should equal the text \"Sloane Juarez\"",
            "match": {
              "location": "src\\step-definitions\\assertions\\verify-new-page.ts:73"
            },
            "result": {
              "status": "passed",
              "duration": 14273399
            }
          },
          {
            "arguments": [],
            "keyword": "And ",
            "line": 18,
            "name": "the \"gender label\" on the \"2nd\" tab should contain the text \"Gender:\"",
            "match": {
              "location": "src\\step-definitions\\assertions\\verify-new-page.ts:51"
            },
            "result": {
              "status": "passed",
              "duration": 5443299
            }
          },
          {
            "arguments": [],
            "keyword": "And ",
            "line": 19,
            "name": "the \"gender\" on the \"2nd\" tab should equal the text \"Female\"",
            "match": {
              "location": "src\\step-definitions\\assertions\\verify-new-page.ts:73"
            },
            "result": {
              "status": "passed",
              "duration": 12283100
            }
          },
          {
            "arguments": [],
            "keyword": "And ",
            "line": 20,
            "name": "the \"address label\" on the \"2nd\" tab should contain the text \"Address:\"",
            "match": {
              "location": "src\\step-definitions\\assertions\\verify-new-page.ts:51"
            },
            "result": {
              "status": "passed",
              "duration": 13176599
            }
          },
          {
            "arguments": [],
            "keyword": "And ",
            "line": 21,
            "name": "the \"address\" on the \"2nd\" tab should equal the text \"8162 Tincidunt Rd., Ludhiana\"",
            "match": {
              "location": "src\\step-definitions\\assertions\\verify-new-page.ts:73"
            },
            "result": {
              "status": "passed",
              "duration": 5331500
            }
          },
          {
            "arguments": [],
            "keyword": "And ",
            "line": 22,
            "name": "the \"edit\" on the \"2nd\" tab should be displayed",
            "match": {
              "location": "src\\step-definitions\\assertions\\verify-new-page.ts:29"
            },
            "result": {
              "status": "passed",
              "duration": 16648600
            }
          },
          {
            "arguments": [],
            "keyword": "And ",
            "line": 23,
            "name": "the \"delete\" on the \"2nd\" tab should be displayed",
            "match": {
              "location": "src\\step-definitions\\assertions\\verify-new-page.ts:29"
            },
            "result": {
              "status": "passed",
              "duration": 18200699
            }
          },
          {
            "keyword": "After",
            "hidden": true,
            "result": {
              "status": "passed",
              "duration": 565860700
            }
          }
        ],
        "tags": [
          {
            "name": "@smoke",
            "line": 4
          },
          {
            "name": "@regression",
            "line": 5
          }
        ],
        "type": "scenario"
      }
    ],
    "id": "as-a-user-i-can-interact-with-tabs",
    "line": 1,
    "keyword": "Feature",
    "name": "As a user I can interact with tabs",
    "tags": [],
    "uri": "src\\features\\playground\\tabs.feature"
  },
  {
    "description": "",
    "elements": [
      {
        "description": "",
        "id": "as-a-user-i-can-interact-with-windows;as-a-user-i-can-interact-and-assert-on-new-windows",
        "keyword": "Scenario",
        "line": 6,
        "name": "As a user I can interact and assert on new windows",
        "steps": [
          {
            "keyword": "Before",
            "hidden": true,
            "result": {
              "status": "passed",
              "duration": 1854643600
            }
          },
          {
            "arguments": [],
            "keyword": "Given ",
            "line": 7,
            "name": "I am on the \"home\" page",
            "match": {
              "location": "src\\step-definitions\\navigation.ts:8"
            },
            "result": {
              "status": "passed",
              "duration": 2617398000
            }
          },
          {
            "arguments": [],
            "keyword": "And ",
            "line": 8,
            "name": "I click the \"playground\" button",
            "match": {
              "location": "src\\step-definitions\\click.ts:10"
            },
            "result": {
              "status": "passed",
              "duration": 542047899
            }
          },
          {
            "arguments": [],
            "keyword": "When ",
            "line": 9,
            "name": "I am directed to the \"playground\" page",
            "match": {
              "location": "src\\step-definitions\\navigation.ts:25"
            },
            "result": {
              "status": "passed",
              "duration": 294500
            }
          },
          {
            "arguments": [],
            "keyword": "And ",
            "line": 10,
            "name": "I click the \"open window\" button",
            "match": {
              "location": "src\\step-definitions\\click.ts:10"
            },
            "result": {
              "status": "passed",
              "duration": 2443704399
            }
          },
          {
            "arguments": [],
            "keyword": "Then ",
            "line": 11,
            "name": "the \"2nd\" window should contain the title \"Contacts\"",
            "match": {
              "location": "src\\step-definitions\\assertions\\verify-new-page.ts:8"
            },
            "result": {
              "status": "passed",
              "duration": 1092861799
            }
          },
          {
            "arguments": [],
            "keyword": "And ",
            "line": 12,
            "name": "the \"1st\" window should contain the title \"Playground\"",
            "match": {
              "location": "src\\step-definitions\\assertions\\verify-new-page.ts:8"
            },
            "result": {
              "status": "passed",
              "duration": 1013519899
            }
          },
          {
            "arguments": [],
            "keyword": "And ",
            "line": 13,
            "name": "I fill in the \"search\" input on the \"2nd\" window with \"Sloane Juarez\"",
            "match": {
              "location": "src\\step-definitions\\page.ts:8"
            },
            "result": {
              "status": "passed",
              "duration": 169117300
            }
          },
          {
            "arguments": [],
            "keyword": "And ",
            "line": 14,
            "name": "the \"contact\" on the \"2nd\" window should be displayed",
            "match": {
              "location": "src\\step-definitions\\assertions\\verify-new-page.ts:29"
            },
            "result": {
              "status": "passed",
              "duration": 31927600
            }
          },
          {
            "arguments": [],
            "keyword": "And ",
            "line": 15,
            "name": "the \"full name label\" on the \"2nd\" window should contain the text \"Name:\"",
            "match": {
              "location": "src\\step-definitions\\assertions\\verify-new-page.ts:51"
            },
            "result": {
              "status": "passed",
              "duration": 17242500
            }
          },
          {
            "arguments": [],
            "keyword": "And ",
            "line": 16,
            "name": "the \"name\" on the \"2nd\" window should equal the text \"Sloane Juarez\"",
            "match": {
              "location": "src\\step-definitions\\assertions\\verify-new-page.ts:73"
            },
            "result": {
              "status": "passed",
              "duration": 21140800
            }
          },
          {
            "arguments": [],
            "keyword": "And ",
            "line": 17,
            "name": "the \"gender label\" on the \"2nd\" window should contain the text \"Gender:\"",
            "match": {
              "location": "src\\step-definitions\\assertions\\verify-new-page.ts:51"
            },
            "result": {
              "status": "passed",
              "duration": 26003400
            }
          },
          {
            "arguments": [],
            "keyword": "And ",
            "line": 18,
            "name": "the \"gender\" on the \"2nd\" window should equal the text \"Female\"",
            "match": {
              "location": "src\\step-definitions\\assertions\\verify-new-page.ts:73"
            },
            "result": {
              "status": "passed",
              "duration": 10576500
            }
          },
          {
            "arguments": [],
            "keyword": "And ",
            "line": 19,
            "name": "the \"address label\" on the \"2nd\" window should contain the text \"Address:\"",
            "match": {
              "location": "src\\step-definitions\\assertions\\verify-new-page.ts:51"
            },
            "result": {
              "status": "passed",
              "duration": 9592900
            }
          },
          {
            "arguments": [],
            "keyword": "And ",
            "line": 20,
            "name": "the \"address\" on the \"2nd\" window should equal the text \"8162 Tincidunt Rd., Ludhiana\"",
            "match": {
              "location": "src\\step-definitions\\assertions\\verify-new-page.ts:73"
            },
            "result": {
              "status": "passed",
              "duration": 11782500
            }
          },
          {
            "arguments": [],
            "keyword": "And ",
            "line": 21,
            "name": "the \"edit\" on the \"2nd\" window should be displayed",
            "match": {
              "location": "src\\step-definitions\\assertions\\verify-new-page.ts:29"
            },
            "result": {
              "status": "passed",
              "duration": 13504499
            }
          },
          {
            "arguments": [],
            "keyword": "And ",
            "line": 22,
            "name": "the \"delete\" on the \"2nd\" window should be displayed",
            "match": {
              "location": "src\\step-definitions\\assertions\\verify-new-page.ts:29"
            },
            "result": {
              "status": "passed",
              "duration": 10641900
            }
          },
          {
            "keyword": "After",
            "hidden": true,
            "result": {
              "status": "passed",
              "duration": 844630000
            }
          }
        ],
        "tags": [
          {
            "name": "@smoke",
            "line": 4
          },
          {
            "name": "@regression",
            "line": 5
          }
        ],
        "type": "scenario"
      }
    ],
    "id": "as-a-user-i-can-interact-with-windows",
    "line": 1,
    "keyword": "Feature",
    "name": "As a user I can interact with windows",
    "tags": [],
    "uri": "src\\features\\playground\\windows.feature"
  }
]